mmwebexp.py
setup.cfg
setup.py
mmwebexp.egg-info/PKG-INFO
mmwebexp.egg-info/SOURCES.txt
mmwebexp.egg-info/dependency_links.txt
mmwebexp.egg-info/entry_points.txt
mmwebexp.egg-info/not-zip-safe
mmwebexp.egg-info/top_level.txt