Metadata-Version: 1.0
Name: mmwebexp
Version: 0.1dev
Summary: A screen scraper to extract subscribers/members from a Mailman web control panel
Home-page: http://pypi.python.org/pypi/mmwebexp/
Author: Randy Syring
Author-email: randy@rcs-comp.com
License: BSD
Platform: UNKNOWN
Classifier: Development Status :: 3 - Alpha
Classifier: Intended Audience :: Developers
Classifier: License :: OSI Approved :: BSD License
